global_entry_alerter/__init__.py
global_entry_alerter/clients/__init__.py
global_entry_alerter/clients/scheduler/__init__.py
global_entry_alerter/clients/scheduler/client.py
global_entry_alerter/clients/twilio/__init__.py
global_entry_alerter/clients/twilio/client.py
global_entry_alerter/main.py
global_entry_alerter-0.2.3.dist-info/WHEEL
global_entry_alerter-0.2.3.dist-info/entry_points.txt
global_entry_alerter-0.2.3.dist-info/METADATA
global_entry_alerter-0.2.3.dist-info/RECORD
