Metadata-Version: 2.1
Name: global-entry-alerter
Version: 0.2.3
Summary: A bot that helps you find an open Global Entry interview appointment
Author: Graham Place
Requires-Python: >=3.8.1,<4
Classifier: Programming Language :: Python :: 3
Classifier: Programming Language :: Python :: 3.9
Classifier: Programming Language :: Python :: 3.10
Classifier: Programming Language :: Python :: 3.11
Requires-Dist: black (>=22.12.0,<23.0.0)
Requires-Dist: flake8 (>=6.0.0,<7.0.0)
Requires-Dist: pre-commit (>=3.0.1,<4.0.0)
Requires-Dist: requests (>=2.28.2,<3.0.0)
Requires-Dist: toml (>=0.10.2,<0.11.0)
Requires-Dist: twilio (>=7.16.2,<8.0.0)
